adw/__init__.py
adw/analyze.py
adw/cli.py
adw/context.py
adw/daemon_state.py
adw/dashboard.py
adw/detect.py
adw/init.py
adw/notifications.py
adw/specs.py
adw/tasks.py
adw/update.py
adw/webhooks.py
adw/agent/__init__.py
adw/agent/environment.py
adw/agent/executor.py
adw/agent/manager.py
adw/agent/model_selector.py
adw/agent/models.py
adw/agent/ports.py
adw/agent/state.py
adw/agent/task_parser.py
adw/agent/task_updater.py
adw/agent/utils.py
adw/agent/worktree.py
adw/commands/__init__.py
adw/commands/completion.py
adw/commands/monitor_commands.py
adw/commands/task_commands.py
adw/hooks/__init__.py
adw/hooks/handlers.py
adw/integrations/__init__.py
adw/integrations/github.py
adw/integrations/qmd.py
adw/plugins/__init__.py
adw/plugins/base.py
adw/plugins/manager.py
adw/plugins/builtins/__init__.py
adw/plugins/builtins/discord/__init__.py
adw/plugins/builtins/github/__init__.py
adw/plugins/builtins/linear/__init__.py
adw/plugins/builtins/qmd/__init__.py
adw/plugins/builtins/slack/__init__.py
adw/protocol/__init__.py
adw/protocol/messages.py
adw/specs/__init__.py
adw/specs/loader.py
adw/specs/models.py
adw/templates/__init__.py
adw/templates/tasks.md
adw/templates/agents/__init__.py
adw/templates/agents/_base.md
adw/templates/agents/backend.md
adw/templates/agents/frontend.md
adw/templates/agents/fullstack.md
adw/templates/commands/__init__.py
adw/templates/commands/approve_spec.md
adw/templates/commands/build.md
adw/templates/commands/discuss.md
adw/templates/commands/implement.md
adw/templates/commands/plan.md
adw/templates/commands/review.md
adw/templates/commands/status.md
adw/templates/commands/update_task.md
adw/templates/commands/verify.md
adw/triggers/__init__.py
adw/triggers/cron.py
adw/triggers/github.py
adw/triggers/webhook.py
adw/tui/__init__.py
adw/tui/app.py
adw/tui/branding.py
adw/tui/commands.py
adw/tui/log_buffer.py
adw/tui/log_formatter.py
adw/tui/log_watcher.py
adw/tui/state.py
adw/tui/styles.py
adw/tui/ink_dist/cli.mjs
adw/tui/widgets/__init__.py
adw_cli-0.5.1.dist-info/METADATA
adw_cli-0.5.1.dist-info/WHEEL
adw_cli-0.5.1.dist-info/entry_points.txt
adw_cli-0.5.1.dist-info/licenses/LICENSE
adw_cli-0.5.1.dist-info/RECORD
