Metadata-Version: 2.4
Name: adw-cli
Version: 0.5.1
Summary: AI Developer Workflow CLI - Orchestrate Claude Code for any project
Project-URL: Homepage, https://github.com/mhmdez/adw
Project-URL: Repository, https://github.com/mhmdez/adw
Project-URL: Issues, https://github.com/mhmdez/adw/issues
Author: StudiBudi
License: MIT
License-File: LICENSE
Keywords: ai,claude,cli,developer-tools,orchestration
Classifier: Development Status :: 4 - Beta
Classifier: Environment :: Console
Classifier: Intended Audience :: Developers
Classifier: License :: OSI Approved :: MIT License
Classifier: Programming Language :: Python :: 3
Classifier: Programming Language :: Python :: 3.11
Classifier: Programming Language :: Python :: 3.12
Classifier: Programming Language :: Python :: 3.13
Classifier: Topic :: Software Development
Classifier: Topic :: Software Development :: Build Tools
Requires-Python: >=3.11
Requires-Dist: click>=8.1.0
Requires-Dist: httpx>=0.25.0
Requires-Dist: pydantic>=2.0.0
Requires-Dist: rich>=13.0.0
Requires-Dist: textual>=0.50.0
Requires-Dist: watchfiles>=0.20.0
Provides-Extra: dev
Requires-Dist: mypy>=1.0.0; extra == 'dev'
Requires-Dist: pytest-cov>=4.0.0; extra == 'dev'
Requires-Dist: pytest>=7.0.0; extra == 'dev'
Requires-Dist: ruff>=0.1.0; extra == 'dev'
